pylity/Async.py
pylity/Collection.py
pylity/Function.py
pylity/Path.py
pylity/String.py
pylity/__init__.py
pylity/decorators/validate_func_params.py
pylity-0.0.11.dist-info/LICENSE
pylity-0.0.11.dist-info/METADATA
pylity-0.0.11.dist-info/WHEEL
pylity-0.0.11.dist-info/RECORD
