Metadata-Version: 2.1
Name: pylity
Version: 0.0.11
Summary: A collection of utility functions for Python. pylity means Python Utility 
Home-page: https://github.com/Payadel/pylity
License: GPLV3
Keywords: utility,helpers
Author: Payadel
Author-email: payadelteam@gmail.com
Requires-Python: >=3.8,<4.0
Classifier: License :: Other/Proprietary License
Classifier: Programming Language :: Python :: 3
Classifier: Programming Language :: Python :: 3.8
Classifier: Programming Language :: Python :: 3.9
Classifier: Programming Language :: Python :: 3.10
Classifier: Programming Language :: Python :: 3.11
Requires-Dist: on-rails (>=4.2.0)
Requires-Dist: schema (>=0.7.5)
Project-URL: Repository, https://github.com/Payadel/pylity
